LICENSE
README.md
setup.py
Hmm/Hmm.py
Hmm/Hmm1.py
Hmm/Hmm2.py
Hmm/HmmState.py
Hmm/__init__.py
NlpToolkit_Hmm.egg-info/PKG-INFO
NlpToolkit_Hmm.egg-info/SOURCES.txt
NlpToolkit_Hmm.egg-info/dependency_links.txt
NlpToolkit_Hmm.egg-info/requires.txt
NlpToolkit_Hmm.egg-info/top_level.txt