Metadata-Version: 2.1
Name: NlpToolkit-Hmm
Version: 1.0.8
Summary: Hidden Markov Model Library
Home-page: https://github.com/StarlangSoftware/Hmm-Py
Author: olcaytaner
Author-email: olcay.yildiz@ozyegin.edu.tr
License: UNKNOWN
Platform: UNKNOWN
License-File: LICENSE
